ccexport.py
ccexport-0.1.1.dist-info/METADATA
ccexport-0.1.1.dist-info/WHEEL
ccexport-0.1.1.dist-info/entry_points.txt
ccexport-0.1.1.dist-info/licenses/LICENSE
ccexport-0.1.1.dist-info/RECORD
