Metadata-Version: 2.4
Name: ccexport
Version: 0.1.1
Summary: Export Claude Code chat history to markdown
Project-URL: Repository, https://github.com/odysseus0/ccexport
Project-URL: Issues, https://github.com/odysseus0/ccexport/issues
Author: odysseus0
License: MIT
License-File: LICENSE
Keywords: claude,claude-code,cli,export,markdown
Classifier: Development Status :: 4 - Beta
Classifier: Environment :: Console
Classifier: Intended Audience :: Developers
Classifier: License :: OSI Approved :: MIT License
Classifier: Operating System :: OS Independent
Classifier: Programming Language :: Python :: 3
Classifier: Programming Language :: Python :: 3.12
Classifier: Topic :: Utilities
Requires-Python: >=3.12
Requires-Dist: typer>=0.16.0
